aiclubiuh/__init__.py
aiclubiuh-0.1.6.dist-info/METADATA
aiclubiuh-0.1.6.dist-info/WHEEL
aiclubiuh-0.1.6.dist-info/top_level.txt
aiclubiuh-0.1.6.dist-info/RECORD
