Metadata-Version: 2.1
Name: aiclubiuh
Version: 0.1.6
Summary: Thư viện hỗ trợ cho AI Club IUH
Home-page: https://main.aiclubiuh.com
Author: htanh
Author-email: anhkhdl@gmail.com
Classifier: Programming Language :: Python :: 3
Classifier: License :: OSI Approved :: MIT License
Classifier: Operating System :: OS Independent
Requires-Python: >=3.6
Requires-Dist: rich >=13.0.0
